atramentarium/__init__.py
atramentarium/atramentarium.py
atramentarium-0.4.dist-info/LICENSE
atramentarium-0.4.dist-info/METADATA
atramentarium-0.4.dist-info/WHEEL
atramentarium-0.4.dist-info/top_level.txt
atramentarium-0.4.dist-info/RECORD
